ergastirio/__init__.py
ergastirio/classes.py
ergastirio/config_default.json
ergastirio/default_settings.json
ergastirio/experiment.py
ergastirio/experiment_gui.py
ergastirio/experiment_initializer.py
ergastirio/logger.py
ergastirio/main.py
ergastirio/panels.py
ergastirio/styles.py
ergastirio/utils.py
ergastirio/examples_config_files/1Lockins_1Powermeter.json
ergastirio/examples_config_files/1Powermeter_1APT.json
ergastirio/examples_config_files/1Powermeter_1APT_1Spect.json
ergastirio/examples_config_files/1Powermeter_1Spect.json
ergastirio/examples_config_files/2Lockins_1Powermeter_1APT.json
ergastirio/graphics/arrow.png
ergastirio/graphics/home.png
ergastirio/graphics/pause.png
ergastirio/graphics/play.png
ergastirio/graphics/settings.png
ergastirio/graphics/wheel.png
ergastirio/widgets/__init__.py
ergastirio/widgets/plot.py
ergastirio/widgets/table.py
ergastirio/widgets/waitingspinnerwidget.py
ergastirio-0.28.dist-info/METADATA
ergastirio-0.28.dist-info/WHEEL
ergastirio-0.28.dist-info/entry_points.txt
ergastirio-0.28.dist-info/top_level.txt
ergastirio-0.28.dist-info/RECORD
