Metadata-Version: 2.1
Name: ergastirio
Version: 0.28
Summary: A python GUI connect several devices and automatize acquisition data in lab.
Home-page: https://github.com/MicheleCotrufo/
Author: Michele Cotrufo
Author-email: michele.cotrufo@gmail.com
License: MIT
Platform: UNKNOWN
Requires-Dist: PyQt5 (>=5.15.6)
Requires-Dist: pyqtgraph (>=0.12.4)
Requires-Dist: abstract-instrument-interface (>=0.9)
Requires-Dist: numpy
Requires-Dist: typing-extensions
